{"name":"Modules.js","tagline":"modules.js","body":"#modules.js framework\r\n###The framework for creating modular web clients\r\n[Main GIT Repository](http://alm.geo4geo.com/gitblit/summary/modules.js.git) (Login: guest , Password: guest)\r\n\r\n[Main Bug Tracker](http://alm.geo4geo.com/youtrack) -> Login as guest -> Issues Page\r\n\r\n[Main Test Server](http://alm.geo4geo.com/teamcity) -> Login as guest\r\n\r\n[Repository @GitHub](https://github.com/trukhinyuri/modules.js)\r\n\r\n[Bugtracker @GitHub](https://github.com/trukhinyuri/modules.js/issues?state=open\")\r\n\r\n[Repository @BitBucket](https://bitbucket.org/trukhinyuri/modules.js)\r\n\r\n[Bugtracker @BitBucket](https://bitbucket.org/trukhinyuri/modules.js/issues?status=new&status=open)\r\n\r\nAPI DOCS path: /jsDoc\r\n\r\n[Please, DONATE to the modules.js project!](https://www.paypal.com/cgi-bin/webscr?cmd=_s-xclick&hosted_button_id=CFZMK8KLFSJC4)\r\n","google":"","note":"Don't delete this file! It's used internally to help with page regeneration."}